composabl_core/trainer_target_enum.cpython-310-aarch64-linux-gnu.so
composabl_core/__init__.cpython-310-aarch64-linux-gnu.so
composabl_core/main.cpython-310-aarch64-linux-gnu.so
composabl_core/trainer_base.cpython-310-aarch64-linux-gnu.so
composabl_core/settings.cpython-310-aarch64-linux-gnu.so
composabl_core/networking/kubernetes_util.cpython-310-aarch64-linux-gnu.so
composabl_core/networking/json_encoder.cpython-310-aarch64-linux-gnu.so
composabl_core/networking/grpc.cpython-310-aarch64-linux-gnu.so
composabl_core/networking/serializer.cpython-310-aarch64-linux-gnu.so
composabl_core/networking/network_mgr.cpython-310-aarch64-linux-gnu.so
composabl_core/networking/subprocess_util.cpython-310-aarch64-linux-gnu.so
composabl_core/networking/deserializer_json.cpython-310-aarch64-linux-gnu.so
composabl_core/networking/http_util.cpython-310-aarch64-linux-gnu.so
composabl_core/networking/episode_manager.cpython-310-aarch64-linux-gnu.so
composabl_core/networking/serializer_json.cpython-310-aarch64-linux-gnu.so
composabl_core/networking/__init__.cpython-310-aarch64-linux-gnu.so
composabl_core/networking/watchdog.cpython-310-aarch64-linux-gnu.so
composabl_core/networking/network_util.cpython-310-aarch64-linux-gnu.so
composabl_core/networking/deserializer.cpython-310-aarch64-linux-gnu.so
composabl_core/networking/exception.cpython-310-aarch64-linux-gnu.so
composabl_core/networking/strategy.cpython-310-aarch64-linux-gnu.so
composabl_core/networking/deserializer_gym_space.cpython-310-aarch64-linux-gnu.so
composabl_core/networking/exception_handler.cpython-310-aarch64-linux-gnu.so
composabl_core/networking/kubernetes_direct_mode_util.cpython-310-aarch64-linux-gnu.so
composabl_core/networking/event_base.cpython-310-aarch64-linux-gnu.so
composabl_core/networking/status_enum.cpython-310-aarch64-linux-gnu.so
composabl_core/networking/base_mgr.cpython-310-aarch64-linux-gnu.so
composabl_core_dev-0.18.1.dist-info/RECORD
composabl_core_dev-0.18.1.dist-info/METADATA
composabl_core_dev-0.18.1.dist-info/WHEEL
composabl_core_dev-0.18.1.dist-info/top_level.txt
