Metadata-Version: 2.4
Name: composabl-core-dev
Version: 0.18.1
Summary: the Composabl core functionality required to apply the Machine Teaching paradigm
Author-email: Hunter Park <hunter@composabl.com>
Requires-Python: >=3.10, <3.13
Requires-Dist: composabl-api-dev>=0.18.1
Requires-Dist: numpy<2.0.0
Requires-Dist: tomli
Requires-Dist: networkx>=3.1
Requires-Dist: grpcio==1.59.0
Requires-Dist: grpcio-tools==1.59.0
Requires-Dist: grpcio-reflection==1.59.0
Requires-Dist: pytest-asyncio
Requires-Dist: fastapi
Requires-Dist: uvicorn
Requires-Dist: gymnasium==0.28.1
Requires-Dist: requests==2.31.0
Requires-Dist: urllib3==1.26.12
Requires-Dist: sentry-sdk
Requires-Dist: segment-analytics-python
Requires-Dist: typer[all]
Requires-Dist: rich
Requires-Dist: Cython==3.0.10
Requires-Dist: cloudpickle==3.0.0
Requires-Dist: docker
Requires-Dist: kubernetes
Requires-Dist: pydantic==2.11.7
Requires-Dist: pydantic-settings
Requires-Dist: paho-mqtt==2.0.0
Requires-Dist: nest-asyncio
Requires-Dist: matplotlib
Requires-Dist: protobuf
Requires-Dist: psutil
Requires-Dist: uvloop==0.22.1
Requires-Dist: aiohttp
Requires-Dist: jwt
Requires-Dist: ruff
Requires-Dist: toml
Requires-Dist: pyarrow==20.0.0
Requires-Dist: redis
Dynamic: description
Dynamic: description-content-type
Dynamic: requires-python
